federatedsecure/services/simon/__init__.py
federatedsecure/services/simon/microservice.py
federatedsecure/services/simon/peer_to_peer.py
federatedsecure/services/simon/sync_api.py
federatedsecure/services/simon/task.py
federatedsecure/services/simon/accumulators/accumulator.py
federatedsecure/services/simon/accumulators/accumulator_basic_array.py
federatedsecure/services/simon/accumulators/accumulator_basic_function.py
federatedsecure/services/simon/accumulators/accumulator_basic_minimum_maximum.py
federatedsecure/services/simon/accumulators/accumulator_basic_sum.py
federatedsecure/services/simon/accumulators/accumulator_generic.py
federatedsecure/services/simon/accumulators/accumulator_generic_dictionary.py
federatedsecure/services/simon/accumulators/accumulator_kth_element.py
federatedsecure/services/simon/accumulators/accumulator_set_intersection.py
federatedsecure/services/simon/accumulators/accumulator_set_intersection_size.py
federatedsecure/services/simon/accumulators/accumulator_set_union.py
federatedsecure/services/simon/accumulators/accumulator_statistics_bivariate.py
federatedsecure/services/simon/accumulators/accumulator_statistics_contingency.py
federatedsecure/services/simon/accumulators/accumulator_statistics_frequency.py
federatedsecure/services/simon/accumulators/accumulator_statistics_moments.py
federatedsecure/services/simon/accumulators/accumulator_statistics_univariate.py
federatedsecure/services/simon/accumulators/create.py
federatedsecure/services/simon/caches/additive.py
federatedsecure/services/simon/caches/cache.py
federatedsecure/services/simon/caches/functional.py
federatedsecure/services/simon/caches/multiplicative.py
federatedsecure/services/simon/crypto/x25519x448.py
federatedsecure/services/simon/microprotocols/create.py
federatedsecure/services/simon/microprotocols/microprotocol.py
federatedsecure/services/simon/microprotocols/microprotocol_kth_element.py
federatedsecure/services/simon/microprotocols/microprotocol_minimum_maximum.py
federatedsecure_simon-0.6.4.dist-info/METADATA
federatedsecure_simon-0.6.4.dist-info/WHEEL
federatedsecure_simon-0.6.4.dist-info/top_level.txt
federatedsecure_simon-0.6.4.dist-info/RECORD
